{
  "project_info": {
    "project_number": "187270884302",
    "firebase_url": "https://agriapp-f01a1.firebaseio.com",
    "project_id": "agriapp-f01a1",
    "storage_bucket": "agriapp-f01a1.appspot.com"
  },
  "client": [
    {
      "client_info": {
        "mobilesdk_app_id": "1:187270884302:android:ebb47efd0062f53549999f",
        "android_client_info": {
          "package_name": "expo.AgriEdgeApp.AgriEdgeApp"
        }
      },
      "oauth_client": [
        {
          "client_id": "187270884302-pao5jef474tv8bese03f3qjnljtr4lan.apps.googleusercontent.com",
          "client_type": 1,
          "android_info": {
            "package_name": "expo.AgriEdgeApp.AgriEdgeApp",
            "certificate_hash": "ec0673217438b7be271247f375576cc51204e12d"
          }
        }
      ],
      "api_key": [
        {
          "current_key": "AIzaSyDTekvIif2O_cVJQTTqViWOP4Y0ncD5plg"
        }
      ],
      "services": {
        "appinvite_service": {
          "other_platform_oauth_client": [
            {
              "client_id": "187270884302-51mta2fot5qekt3792ogg427d28blt91.apps.googleusercontent.com",
              "client_type": 3
            }
          ]
        }
      }
    }
  ],
  "configuration_version": "1"
}